{
    "subjectName": "duanesthesia",
    "lectures": [
        {
            "title": "1. Preoperative assessment and preparation, airway management Live on: 05:00 pm 05 Apr, 2024.mp4",
            "streamingUrl": "https://web.afrahtafreeh.site/prepare/w0ozv6q0HVUbapXjTZQswQ?type=stream",
            "downloadUrl": "https://web.afrahtafreeh.site/prepare/w0ozv6q0HVUbapXjTZQswQ?type=download"
        },
        {
            "title": "1.Airway management (ETT), monitoring under anesthesia part 1 Live on: 05:00 pm 05 Apr, 2024",
            "streamingUrl": "https://web.afrahtafreeh.site/prepare/uJrAxGNtgCkyeKzewZAzlQ?type=stream",
            "downloadUrl": "https://web.afrahtafreeh.site/prepare/uJrAxGNtgCkyeKzewZAzlQ?type=download"
        },
        {
            "title": "2. Capnography, iv induction agents Live on: 03:00 pm 06 Apr, 2024",
            "streamingUrl": "https://web.afrahtafreeh.site/prepare/luTdgAt-biHGD8g0tuy0ww?type=stream",
            "downloadUrl": "https://web.afrahtafreeh.site/prepare/luTdgAt-biHGD8g0tuy0ww?type=download"
        },
        {
            "title": "2. Muscle relaxants & neuromuscular monitoring Live on: 03:00 pm 06 Apr, 2024",
            "streamingUrl": "https://web.afrahtafreeh.site/prepare/SmV_Z7OqGl_OV6eF7IPRQQ?type=stream",
            "downloadUrl": "https://web.afrahtafreeh.site/prepare/SmV_Z7OqGl_OV6eF7IPRQQ?type=download"
        },
        {
            "title": "2. Inhaled anesthetic agents part 1 Live on: 03:00 pm 06 Apr, 2024",
            "streamingUrl": "https://web.afrahtafreeh.site/prepare/UI_Fai_s-q3i4Ta3psYq2A?type=stream",
            "downloadUrl": "https://web.afrahtafreeh.site/prepare/UI_Fai_s-q3i4Ta3psYq2A?type=download"
        },
        {
            "title": "3.Individual inhaled anesthetic agents + anesthesia delivery systems Live on: 05:00 pm 07 Apr, 2024",
            "streamingUrl": "https://web.afrahtafreeh.site/prepare/yIYp9DLey3HiKjWWmkRWIg?type=stream",
            "downloadUrl": "https://web.afrahtafreeh.site/prepare/yIYp9DLey3HiKjWWmkRWIg?type=download"
        },
        {
            "title": "3.1-Complications associated with anesthesia Live on: 05:00 pm 07 Apr, 2024",
            "streamingUrl": "https://web.afrahtafreeh.site/prepare/BfdpMkpd6WoGG4gCtteKGg?type=stream",
            "downloadUrl": "https://web.afrahtafreeh.site/prepare/BfdpMkpd6WoGG4gCtteKGg?type=download"
        },
        {
            "title": "4.local anesthetics and regional anesthesia Live on: 05:00 pm 08 Apr, 2024",
            "streamingUrl": "https://web.afrahtafreeh.site/prepare/hNf3l0dppRm1eD1nvuEtsA?type=stream",
            "downloadUrl": "https://web.afrahtafreeh.site/prepare/hNf3l0dppRm1eD1nvuEtsA?type=download"
        },
        {
            "title": "4. Critical care, miscellaneous topics and CPR Live on: 05:00 pm 08 Apr, 2024",
            "streamingUrl": "https://web.afrahtafreeh.site/prepare/vuTcLDrJ6s4_wEz8e9fE_g?type=stream",
            "downloadUrl": "https://web.afrahtafreeh.site/prepare/vuTcLDrJ6s4_wEz8e9fE_g?type=download"
        },
        {
            "title": "1.1 Airway assessment and airway management ( facemask and supraglottic airway devices).mp4 Live on - 05:00 pm 27 September 2024",
            "streamingUrl": "https://web.afrahtafreeh.site/prepare/j3T4hWLeW8tvXpcWGhSQtw?type=stream",
            "downloadUrl": "https://web.afrahtafreeh.site/prepare/j3T4hWLeW8tvXpcWGhSQtw?type=download"
        },
        {
            "title": "1.2 Endotracheal tube,pre operative preparation, pre medication and pre oxygenation .mp4 Live on - 05:00 pm 27 September 2024",
            "streamingUrl": "https://web.afrahtafreeh.site/prepare/PTfZ36F4SLsuxtlT-_3lKg?type=stream",
            "downloadUrl": "https://web.afrahtafreeh.site/prepare/PTfZ36F4SLsuxtlT-_3lKg?type=download"
        },
        {
            "title": "2.1: Monitoring Under Anesthesia, Thiopentone & Ketamine",
            "streamingUrl": "https://web.afrahtafreeh.site/prepare/Zy9hQdJsTn75apw_2NvLrw?type=stream",
            "downloadUrl": "https://web.afrahtafreeh.site/prepare/Zy9hQdJsTn75apw_2NvLrw?type=download"
        },
        {
            "title": "2.2: Propofol, Etomidate, Scoline and NDMR",
            "streamingUrl": "https://web.afrahtafreeh.site/prepare/ezzH_2XV-lcZnM5VMqblPw?type=stream",
            "downloadUrl": "https://web.afrahtafreeh.site/prepare/ezzH_2XV-lcZnM5VMqblPw?type=download"
        },
        {
            "title": "2.3: Reversal of Neuro Muscular Block & Neuromuscular Monitoring",
            "streamingUrl": "https://web.afrahtafreeh.site/prepare/rW9ee1QSii1uGABW0Yrhbw?type=stream",
            "downloadUrl": "https://web.afrahtafreeh.site/prepare/rW9ee1QSii1uGABW0Yrhbw?type=download"
        },
        {
            "title": "3.1: Inhaled Anesthetic Agent - Pharmacokinetics Part 1",
            "streamingUrl": "https://web.afrahtafreeh.site/prepare/CwL7AGEdAwJKkON4EiVAGw?type=stream",
            "downloadUrl": "https://web.afrahtafreeh.site/prepare/CwL7AGEdAwJKkON4EiVAGw?type=download"
        },
        {
            "title": "3.2: Inhaled Anesthetic Agent - Pharmacokinetics Part 2, Nitrous Oxide, Xenon and Volatile Anesthetic Agents",
            "streamingUrl": "https://web.afrahtafreeh.site/prepare/heP9vXt71qLhZ46V5HQweg?type=stream",
            "downloadUrl": "https://web.afrahtafreeh.site/prepare/heP9vXt71qLhZ46V5HQweg?type=download"
        },
        {
            "title": "3.3: Anesthesia Delivery Systems, Complications Part 1",
            "streamingUrl": "https://web.afrahtafreeh.site/prepare/HqiNkEN4Y2MibbE3YVuq1g?type=stream",
            "downloadUrl": "https://web.afrahtafreeh.site/prepare/HqiNkEN4Y2MibbE3YVuq1g?type=download"
        },
        {
            "title": "3.4: Complications Part 2",
            "streamingUrl": "https://web.afrahtafreeh.site/prepare/YUl6E0LssGlasSp0ieON0w?type=stream",
            "downloadUrl": "https://web.afrahtafreeh.site/prepare/YUl6E0LssGlasSp0ieON0w?type=download"
        },
        {
            "title": "4.1 local anesthetics and regional anesthesia.mp4",
            "streamingUrl": "https://web.afrahtafreeh.site/prepare/dCftmvQ8kkcdN6sx69I1Fw?type=stream",
            "downloadUrl": "https://web.afrahtafreeh.site/prepare/dCftmvQ8kkcdN6sx69I1Fw?type=download"
        },
        {
            "title": "4.2 local anesthetics and regional anesthesia.mp4",
            "streamingUrl": "https://web.afrahtafreeh.site/prepare/9lrUtNJ4AtMNNFtXEFg0vw?type=stream",
            "downloadUrl": "https://web.afrahtafreeh.site/prepare/9lrUtNJ4AtMNNFtXEFg0vw?type=download"
        },
        {
            "title": "1.1 Airway assessment, face mask & supraglottic airway devices.mp4",
            "streamingUrl": "https://web.afrahtafreeh.site/prepare/gWCHYng1gIA1kXaP5200Vw?type=stream",
            "downloadUrl": "https://web.afrahtafreeh.site/prepare/gWCHYng1gIA1kXaP5200Vw?type=download"
        },
        {
            "title": "1.2 Endotracheal tubes, risk assessment, preoperative preparation, monitoring under Anesthesia.mp4",
            "streamingUrl": "https://web.afrahtafreeh.site/prepare/-bYkiwNE6B9ShlKJxpjlWg?type=stream",
            "downloadUrl": "https://web.afrahtafreeh.site/prepare/-bYkiwNE6B9ShlKJxpjlWg?type=download"
        },
        {
            "title": "2.1 Capnography & iv induction agents.mp4",
            "streamingUrl": "https://web.afrahtafreeh.site/prepare/OPFmfiGwMeMeCkqniqSuAw?type=stream",
            "downloadUrl": "https://web.afrahtafreeh.site/prepare/OPFmfiGwMeMeCkqniqSuAw?type=download"
        },
        {
            "title": "2.2 Muscle relaxants and reversal agents .mp4",
            "streamingUrl": "https://web.afrahtafreeh.site/prepare/OIJrJl9pv_txPWFVA5EEyA?type=stream",
            "downloadUrl": "https://web.afrahtafreeh.site/prepare/OIJrJl9pv_txPWFVA5EEyA?type=download"
        },
        {
            "title": "2.3 Neuro muscular monitoring.mp4",
            "streamingUrl": "https://web.afrahtafreeh.site/prepare/3JRBMJrojWbPz1JCy1H5bA?type=stream",
            "downloadUrl": "https://web.afrahtafreeh.site/prepare/3JRBMJrojWbPz1JCy1H5bA?type=download"
        },
        {
            "title": "3. Anaesthesia ultimate live.mp4",
            "streamingUrl": "https://web.afrahtafreeh.site/prepare/ljc8fewgd0Rsww2v6JJk4Q?type=stream",
            "downloadUrl": "https://web.afrahtafreeh.site/prepare/ljc8fewgd0Rsww2v6JJk4Q?type=download"
        },
        {
            "title": "4.1 Complications associated with anesthesia.mp4",
            "streamingUrl": "https://web.afrahtafreeh.site/prepare/zuopNk6WvHuF1FgceVNueA?type=stream",
            "downloadUrl": "https://web.afrahtafreeh.site/prepare/zuopNk6WvHuF1FgceVNueA?type=download"
        },
        {
            "title": "4.2 Local anesthetics and regional Anesthesia.mp4",
            "streamingUrl": "https://web.afrahtafreeh.site/prepare/BhoEJQ7Qg7GnwVvcketiAA?type=stream",
            "downloadUrl": "https://web.afrahtafreeh.site/prepare/BhoEJQ7Qg7GnwVvcketiAA?type=download"
        },
        {
            "title": "4.3 Miscellaneous topics and CPR.mp4",
            "streamingUrl": "https://web.afrahtafreeh.site/prepare/d_ReYHp2mGg2ksi30aMVQg?type=stream",
            "downloadUrl": "https://web.afrahtafreeh.site/prepare/d_ReYHp2mGg2ksi30aMVQg?type=download"
        }
    ],
    "skipped": []
}