{
    "subjectName": "duradiology",
    "lectures": [
        {
            "title": "1.1 CT brain,hemorrhage and infarct.mp4",
            "streamingUrl": "https://web.afrahtafreeh.site/prepare/0kB6KrPd6z1GHMS2UmClFQ?type=stream",
            "downloadUrl": "https://web.afrahtafreeh.site/prepare/0kB6KrPd6z1GHMS2UmClFQ?type=download"
        },
        {
            "title": "1.2 CTA, Cardiac CT, Dual energy CT basics MRI.mp4",
            "streamingUrl": "https://web.afrahtafreeh.site/prepare/WJFV7XeO27wvjoKHutAd6g?type=stream",
            "downloadUrl": "https://web.afrahtafreeh.site/prepare/WJFV7XeO27wvjoKHutAd6g?type=download"
        },
        {
            "title": "1.3 MRI - Advances.mp4",
            "streamingUrl": "https://web.afrahtafreeh.site/prepare/t4pE9C1VILNkBUHzSXXhyQ?type=stream",
            "downloadUrl": "https://web.afrahtafreeh.site/prepare/t4pE9C1VILNkBUHzSXXhyQ?type=download"
        },
        {
            "title": "2.1 Neuraradiology.mp4",
            "streamingUrl": "https://web.afrahtafreeh.site/prepare/Z3hcZl3G5-nEwGgJuyc8Vg?type=stream",
            "downloadUrl": "https://web.afrahtafreeh.site/prepare/Z3hcZl3G5-nEwGgJuyc8Vg?type=download"
        },
        {
            "title": "3.1 chest xray basics.mp4",
            "streamingUrl": "https://web.afrahtafreeh.site/prepare/NO6MaCdKJ5a3wgEXW7ggDQ?type=stream",
            "downloadUrl": "https://web.afrahtafreeh.site/prepare/NO6MaCdKJ5a3wgEXW7ggDQ?type=download"
        },
        {
            "title": "3.2 Common pulmonary pathologies.mp4",
            "streamingUrl": "https://web.afrahtafreeh.site/prepare/ikz9QJyNSUT_IVYymd7tow?type=stream",
            "downloadUrl": "https://web.afrahtafreeh.site/prepare/ikz9QJyNSUT_IVYymd7tow?type=download"
        },
        {
            "title": "3.3 Cardiac imaging.mp4",
            "streamingUrl": "https://web.afrahtafreeh.site/prepare/fUG15Vo1emrtVsBmcZZwGA?type=stream",
            "downloadUrl": "https://web.afrahtafreeh.site/prepare/fUG15Vo1emrtVsBmcZZwGA?type=download"
        },
        {
            "title": "3.4 Bone tumour introduction.mp4",
            "streamingUrl": "https://web.afrahtafreeh.site/prepare/Kc8B9w1ZvpNRi8fde54elg?type=stream",
            "downloadUrl": "https://web.afrahtafreeh.site/prepare/Kc8B9w1ZvpNRi8fde54elg?type=download"
        },
        {
            "title": "4.1-Approach to Focal Bone Lesion Live on: 04:40 pm 15 May, 2024",
            "streamingUrl": "https://web.afrahtafreeh.site/prepare/YtKnBUWEvg9lNZW2RZo8pA?type=stream",
            "downloadUrl": "https://web.afrahtafreeh.site/prepare/YtKnBUWEvg9lNZW2RZo8pA?type=download"
        },
        {
            "title": "4.2 Metabolic Arthritis Miscellaneous Live on: 04:40 pm 15 May, 2024",
            "streamingUrl": "https://web.afrahtafreeh.site/prepare/Uwng4eHmE1LDlQuRAd-Jpw?type=stream",
            "downloadUrl": "https://web.afrahtafreeh.site/prepare/Uwng4eHmE1LDlQuRAd-Jpw?type=download"
        },
        {
            "title": "4.3 Ultrasound Doppler Live on: 04:40 pm 15 May, 2024",
            "streamingUrl": "https://web.afrahtafreeh.site/prepare/V-KQWQC1Ai8OfulHySp5Xw?type=stream",
            "downloadUrl": "https://web.afrahtafreeh.site/prepare/V-KQWQC1Ai8OfulHySp5Xw?type=download"
        },
        {
            "title": "5.1 Urinary tract imaging.mp4",
            "streamingUrl": "https://web.afrahtafreeh.site/prepare/fUd_a8dcpZchDsME5qd5SQ?type=stream",
            "downloadUrl": "https://web.afrahtafreeh.site/prepare/fUd_a8dcpZchDsME5qd5SQ?type=download"
        },
        {
            "title": "5.2 UGI pathologies on barium.mp4",
            "streamingUrl": "https://web.afrahtafreeh.site/prepare/-CurX5o-5zj5dbrskqiwlg?type=stream",
            "downloadUrl": "https://web.afrahtafreeh.site/prepare/-CurX5o-5zj5dbrskqiwlg?type=download"
        },
        {
            "title": "5.3 lower GIT imaging liver pancreas.mp4",
            "streamingUrl": "https://web.afrahtafreeh.site/prepare/0emElwN_3nT-gsTxPkV3Nw?type=stream",
            "downloadUrl": "https://web.afrahtafreeh.site/prepare/0emElwN_3nT-gsTxPkV3Nw?type=download"
        },
        {
            "title": "5.4 Breast imaging.mp4",
            "streamingUrl": "https://web.afrahtafreeh.site/prepare/Ffk-meCHhD0DcOccqt7Dwg?type=stream",
            "downloadUrl": "https://web.afrahtafreeh.site/prepare/Ffk-meCHhD0DcOccqt7Dwg?type=download"
        },
        {
            "title": "5.5 PET scan.mp4",
            "streamingUrl": "https://web.afrahtafreeh.site/prepare/hhj7W64AIEfrOjQWgYXMqA?type=stream",
            "downloadUrl": "https://web.afrahtafreeh.site/prepare/hhj7W64AIEfrOjQWgYXMqA?type=download"
        },
        {
            "title": "6.1 Radioisotopes, Radiation Therapy Live on: 04:45 pm 29 May, 2024",
            "streamingUrl": "https://web.afrahtafreeh.site/prepare/IN9wSqangWoYOXZoiajkzw?type=stream",
            "downloadUrl": "https://web.afrahtafreeh.site/prepare/IN9wSqangWoYOXZoiajkzw?type=download"
        },
        {
            "title": "6.2 Basics of Xrays Radiotherapy & Advances.mp4",
            "streamingUrl": "https://web.afrahtafreeh.site/prepare/OqqoShaKf2CxfWdrHHijwg?type=stream",
            "downloadUrl": "https://web.afrahtafreeh.site/prepare/OqqoShaKf2CxfWdrHHijwg?type=download"
        },
        {
            "title": "6.4 Post class test.mp4",
            "streamingUrl": "https://web.afrahtafreeh.site/prepare/TycyK7hrouuYxaQnCF7pgg?type=stream",
            "downloadUrl": "https://web.afrahtafreeh.site/prepare/TycyK7hrouuYxaQnCF7pgg?type=download"
        },
        {
            "title": "01. CT brain anatomy integration.mp4",
            "streamingUrl": "https://web.afrahtafreeh.site/prepare/O6xE-VKF0X01-gBWGh6unQ?type=stream",
            "downloadUrl": "https://web.afrahtafreeh.site/prepare/O6xE-VKF0X01-gBWGh6unQ?type=download"
        },
        {
            "title": "1.1 Brain hemorrhage, infarct, CTA stroke.mp4",
            "streamingUrl": "https://web.afrahtafreeh.site/prepare/-IzlCwqsqhD0nXbZVGxDUA?type=stream",
            "downloadUrl": "https://web.afrahtafreeh.site/prepare/-IzlCwqsqhD0nXbZVGxDUA?type=download"
        },
        {
            "title": "1.2 MRI basics.mp4",
            "streamingUrl": "https://web.afrahtafreeh.site/prepare/oh9BLCkUXL8VStmgjISqzQ?type=stream",
            "downloadUrl": "https://web.afrahtafreeh.site/prepare/oh9BLCkUXL8VStmgjISqzQ?type=download"
        },
        {
            "title": "2 MRI advances.mp4",
            "streamingUrl": "https://web.afrahtafreeh.site/prepare/265L_fwKk-V0uCAOFT8OSA?type=stream",
            "downloadUrl": "https://web.afrahtafreeh.site/prepare/265L_fwKk-V0uCAOFT8OSA?type=download"
        },
        {
            "title": "2.1 Neuroradiology - infections, Parkinson's, MS.mp4",
            "streamingUrl": "https://web.afrahtafreeh.site/prepare/JU5eth69UE1OQ-F74gUMvg?type=stream",
            "downloadUrl": "https://web.afrahtafreeh.site/prepare/JU5eth69UE1OQ-F74gUMvg?type=download"
        },
        {
            "title": "2.2 Brain tumor, neurocutaneous syndrome.mp4",
            "streamingUrl": "https://web.afrahtafreeh.site/prepare/pkmdEDlzfJ6VxD1FmFWLHA?type=stream",
            "downloadUrl": "https://web.afrahtafreeh.site/prepare/pkmdEDlzfJ6VxD1FmFWLHA?type=download"
        },
        {
            "title": "3.1 CXR basics and approach.mp4",
            "streamingUrl": "https://web.afrahtafreeh.site/prepare/x0Z6mmsKv1BQ75jXOYFkzw?type=stream",
            "downloadUrl": "https://web.afrahtafreeh.site/prepare/x0Z6mmsKv1BQ75jXOYFkzw?type=download"
        },
        {
            "title": "3.2 CXR disease approach.mp4",
            "streamingUrl": "https://web.afrahtafreeh.site/prepare/tHYy35W4088QUouk6vAQPg?type=stream",
            "downloadUrl": "https://web.afrahtafreeh.site/prepare/tHYy35W4088QUouk6vAQPg?type=download"
        },
        {
            "title": "3.4 Cardiac Imaging.mp4",
            "streamingUrl": "https://web.afrahtafreeh.site/prepare/VGyvGGFD_l5FGsYM8nHziQ?type=stream",
            "downloadUrl": "https://web.afrahtafreeh.site/prepare/VGyvGGFD_l5FGsYM8nHziQ?type=download"
        },
        {
            "title": "4.1 Approach to bone tumor.mp4",
            "streamingUrl": "https://web.afrahtafreeh.site/prepare/m0pDeTr2asig_nd9VubLnQ?type=stream",
            "downloadUrl": "https://web.afrahtafreeh.site/prepare/m0pDeTr2asig_nd9VubLnQ?type=download"
        },
        {
            "title": "4.2 Infections, metabolic, arthritis, miscellaneous.mp4",
            "streamingUrl": "https://web.afrahtafreeh.site/prepare/2VjX6mC1w8rdTsTZTd13pw?type=stream",
            "downloadUrl": "https://web.afrahtafreeh.site/prepare/2VjX6mC1w8rdTsTZTd13pw?type=download"
        },
        {
            "title": "4.3 Ultrasound, Doppler.mp4",
            "streamingUrl": "https://web.afrahtafreeh.site/prepare/kQhBSBh7AiRhvx9voiwxaw?type=stream",
            "downloadUrl": "https://web.afrahtafreeh.site/prepare/kQhBSBh7AiRhvx9voiwxaw?type=download"
        },
        {
            "title": "5.1 Urinary tract imaging.mp4",
            "streamingUrl": "https://web.afrahtafreeh.site/prepare/1HLMumwootR7xB7VkbvGWg?type=stream",
            "downloadUrl": "https://web.afrahtafreeh.site/prepare/1HLMumwootR7xB7VkbvGWg?type=download"
        },
        {
            "title": "5.2 Upper GI imaging.mp4",
            "streamingUrl": "https://web.afrahtafreeh.site/prepare/nYFZi6AH_he-cARBSM4jng?type=stream",
            "downloadUrl": "https://web.afrahtafreeh.site/prepare/nYFZi6AH_he-cARBSM4jng?type=download"
        },
        {
            "title": "5.3 Lower GI imaging.mp4",
            "streamingUrl": "https://web.afrahtafreeh.site/prepare/YWxAJnBY_eH_fxogMw7wFA?type=stream",
            "downloadUrl": "https://web.afrahtafreeh.site/prepare/YWxAJnBY_eH_fxogMw7wFA?type=download"
        },
        {
            "title": "5.4 Mamoography.mp4",
            "streamingUrl": "https://web.afrahtafreeh.site/prepare/0jS5H0Z9fHFVEbBW7tjkUg?type=stream",
            "downloadUrl": "https://web.afrahtafreeh.site/prepare/0jS5H0Z9fHFVEbBW7tjkUg?type=download"
        },
        {
            "title": "5.5 PET.mp4",
            "streamingUrl": "https://web.afrahtafreeh.site/prepare/wpvFuwD-w7KMa5hbLPNJOw?type=stream",
            "downloadUrl": "https://web.afrahtafreeh.site/prepare/wpvFuwD-w7KMa5hbLPNJOw?type=download"
        },
        {
            "title": "6.1 Radiotherapy Nuclear Scan.mp4",
            "streamingUrl": "https://web.afrahtafreeh.site/prepare/S5RgJ853oh8D7DxTBeQMyQ?type=stream",
            "downloadUrl": "https://web.afrahtafreeh.site/prepare/S5RgJ853oh8D7DxTBeQMyQ?type=download"
        },
        {
            "title": "6.2 Radiotherapy LINAC Xrays.mp4",
            "streamingUrl": "https://web.afrahtafreeh.site/prepare/ss8e_aQ1wTVYdiATni7Riw?type=stream",
            "downloadUrl": "https://web.afrahtafreeh.site/prepare/ss8e_aQ1wTVYdiATni7Riw?type=download"
        },
        {
            "title": "6.3 Post Class Test.mp4",
            "streamingUrl": "https://web.afrahtafreeh.site/prepare/nvfHzCSTkDIxhpB08TYmYw?type=stream",
            "downloadUrl": "https://web.afrahtafreeh.site/prepare/nvfHzCSTkDIxhpB08TYmYw?type=download"
        }
    ],
    "skipped": []
}