{
    "subjectName": "mobgy",
    "lectures": [
        {
            "title": "1. How to study Obg",
            "streamingUrl": "https://web.afrahtafreeh.site/prepare/exJnCv3sPO9_nFMPGGc_TA?type=stream",
            "downloadUrl": "https://web.afrahtafreeh.site/prepare/exJnCv3sPO9_nFMPGGc_TA?type=download"
        },
        {
            "title": "2 Gametogenesis",
            "streamingUrl": "https://web.afrahtafreeh.site/prepare/zkjVLqVsLJ0nAfr6OJtjFA?type=stream",
            "downloadUrl": "https://web.afrahtafreeh.site/prepare/zkjVLqVsLJ0nAfr6OJtjFA?type=download"
        },
        {
            "title": "3 Fertilisation and Implantation",
            "streamingUrl": "https://web.afrahtafreeh.site/prepare/ryBaGOSZMgvYXWHh92U3uQ?type=stream",
            "downloadUrl": "https://web.afrahtafreeh.site/prepare/ryBaGOSZMgvYXWHh92U3uQ?type=download"
        },
        {
            "title": "4. Teratogenic exposure of conceptus",
            "streamingUrl": "https://web.afrahtafreeh.site/prepare/-7mJu89Bxfs6voXDWigTdw?type=stream",
            "downloadUrl": "https://web.afrahtafreeh.site/prepare/-7mJu89Bxfs6voXDWigTdw?type=download"
        },
        {
            "title": "5 fetus",
            "streamingUrl": "https://web.afrahtafreeh.site/prepare/-7PpaGIQB3FXCETS4LGC5g?type=stream",
            "downloadUrl": "https://web.afrahtafreeh.site/prepare/-7PpaGIQB3FXCETS4LGC5g?type=download"
        },
        {
            "title": "6. Placenta",
            "streamingUrl": "https://web.afrahtafreeh.site/prepare/9Bn33Tz-4GFBja452pJdxg?type=stream",
            "downloadUrl": "https://web.afrahtafreeh.site/prepare/9Bn33Tz-4GFBja452pJdxg?type=download"
        },
        {
            "title": "7. Placental Functions",
            "streamingUrl": "https://web.afrahtafreeh.site/prepare/ftuw4l4IpWy6BugWwcXDTw?type=stream",
            "downloadUrl": "https://web.afrahtafreeh.site/prepare/ftuw4l4IpWy6BugWwcXDTw?type=download"
        },
        {
            "title": "8. Placental anomalies",
            "streamingUrl": "https://web.afrahtafreeh.site/prepare/rsPEoEsNOS85NXaphyJpbQ?type=stream",
            "downloadUrl": "https://web.afrahtafreeh.site/prepare/rsPEoEsNOS85NXaphyJpbQ?type=download"
        },
        {
            "title": "9 Cord and Anomalies",
            "streamingUrl": "https://web.afrahtafreeh.site/prepare/cCckqMFLWd8cYLMKv_ofpQ?type=stream",
            "downloadUrl": "https://web.afrahtafreeh.site/prepare/cCckqMFLWd8cYLMKv_ofpQ?type=download"
        },
        {
            "title": "10 amnitic fluid",
            "streamingUrl": "https://web.afrahtafreeh.site/prepare/gj4kfGZPWQ59n6qIFnf9mQ?type=stream",
            "downloadUrl": "https://web.afrahtafreeh.site/prepare/gj4kfGZPWQ59n6qIFnf9mQ?type=download"
        },
        {
            "title": "11 amniotic fluid",
            "streamingUrl": "https://web.afrahtafreeh.site/prepare/P7Gkguv-M1kxfvGl1-UNUg?type=stream",
            "downloadUrl": "https://web.afrahtafreeh.site/prepare/P7Gkguv-M1kxfvGl1-UNUg?type=download"
        },
        {
            "title": "12 Antenatal patients - History",
            "streamingUrl": "https://web.afrahtafreeh.site/prepare/ZZuNTh0X_T7RfqtFOWIS5A?type=stream",
            "downloadUrl": "https://web.afrahtafreeh.site/prepare/ZZuNTh0X_T7RfqtFOWIS5A?type=download"
        },
        {
            "title": "13 Antenatal patients - Signs, Symptoms and Minor ailments",
            "streamingUrl": "https://web.afrahtafreeh.site/prepare/3DbM4Fy_9e5JmKlTSmtjJA?type=stream",
            "downloadUrl": "https://web.afrahtafreeh.site/prepare/3DbM4Fy_9e5JmKlTSmtjJA?type=download"
        },
        {
            "title": "14 Antenatal patient - Investigations and Advice",
            "streamingUrl": "https://web.afrahtafreeh.site/prepare/i9L_I4dGbqWPxR2zo0EyRQ?type=stream",
            "downloadUrl": "https://web.afrahtafreeh.site/prepare/i9L_I4dGbqWPxR2zo0EyRQ?type=download"
        },
        {
            "title": "15 aneuploid",
            "streamingUrl": "https://web.afrahtafreeh.site/prepare/j5_CQELp4xVRet-mmCYJ6Q?type=stream",
            "downloadUrl": "https://web.afrahtafreeh.site/prepare/j5_CQELp4xVRet-mmCYJ6Q?type=download"
        },
        {
            "title": "16 fetal monitoring",
            "streamingUrl": "https://web.afrahtafreeh.site/prepare/NxA98njwM0fTS3C7iIj8Iw?type=stream",
            "downloadUrl": "https://web.afrahtafreeh.site/prepare/NxA98njwM0fTS3C7iIj8Iw?type=download"
        },
        {
            "title": "17. Maternal adaptation in pregnancy",
            "streamingUrl": "https://web.afrahtafreeh.site/prepare/v1N7chbV44yXkmAkyytvDg?type=stream",
            "downloadUrl": "https://web.afrahtafreeh.site/prepare/v1N7chbV44yXkmAkyytvDg?type=download"
        },
        {
            "title": "18 Obstetrics Pharmacology Integration",
            "streamingUrl": "https://web.afrahtafreeh.site/prepare/ql97Y9QdawgoOqhNNqNc-Q?type=stream",
            "downloadUrl": "https://web.afrahtafreeh.site/prepare/ql97Y9QdawgoOqhNNqNc-Q?type=download"
        },
        {
            "title": "19. Obstetrics Radiology Integration Part 1",
            "streamingUrl": "https://web.afrahtafreeh.site/prepare/MB3ElMpvBHNRlmjTPsNo9w?type=stream",
            "downloadUrl": "https://web.afrahtafreeh.site/prepare/MB3ElMpvBHNRlmjTPsNo9w?type=download"
        },
        {
            "title": "20. Obstetrics Radiology Integration part 2",
            "streamingUrl": "https://web.afrahtafreeh.site/prepare/3TOphU9bSM7PyHNJROgTpw?type=stream",
            "downloadUrl": "https://web.afrahtafreeh.site/prepare/3TOphU9bSM7PyHNJROgTpw?type=download"
        },
        {
            "title": "21. Obstetrics Medicine Integration",
            "streamingUrl": "https://web.afrahtafreeh.site/prepare/sSvsYfp4ALt2bNOq4z0V1Q?type=stream",
            "downloadUrl": "https://web.afrahtafreeh.site/prepare/sSvsYfp4ALt2bNOq4z0V1Q?type=download"
        },
        {
            "title": "22 anemia 1",
            "streamingUrl": "https://web.afrahtafreeh.site/prepare/S7WJfdw2q6w9Dm75N-pEPA?type=stream",
            "downloadUrl": "https://web.afrahtafreeh.site/prepare/S7WJfdw2q6w9Dm75N-pEPA?type=download"
        },
        {
            "title": "23 Anemia in pregnancy: Part 2",
            "streamingUrl": "https://web.afrahtafreeh.site/prepare/on9lR-lRXAZ149KVRLydmw?type=stream",
            "downloadUrl": "https://web.afrahtafreeh.site/prepare/on9lR-lRXAZ149KVRLydmw?type=download"
        },
        {
            "title": "24 Diabetes in pregnancy. Part 1",
            "streamingUrl": "https://web.afrahtafreeh.site/prepare/u3sUZ16gSOsp6iJ7v8pu-g?type=stream",
            "downloadUrl": "https://web.afrahtafreeh.site/prepare/u3sUZ16gSOsp6iJ7v8pu-g?type=download"
        },
        {
            "title": "25 Diabetes in pregnancy. Part 2",
            "streamingUrl": "https://web.afrahtafreeh.site/prepare/cRZVyQOl92yroyWwp58E9A?type=stream",
            "downloadUrl": "https://web.afrahtafreeh.site/prepare/cRZVyQOl92yroyWwp58E9A?type=download"
        },
        {
            "title": "26 Hypertension in pregnancy. Part 1",
            "streamingUrl": "https://web.afrahtafreeh.site/prepare/7nmJfp5w9EqQVSxDtAXgrw?type=stream",
            "downloadUrl": "https://web.afrahtafreeh.site/prepare/7nmJfp5w9EqQVSxDtAXgrw?type=download"
        },
        {
            "title": "27 Hypertension in pregnancy: Part 2",
            "streamingUrl": "https://web.afrahtafreeh.site/prepare/rhkEPvUlVBksk2fJasoZ5g?type=stream",
            "downloadUrl": "https://web.afrahtafreeh.site/prepare/rhkEPvUlVBksk2fJasoZ5g?type=download"
        },
        {
            "title": "28. IUGR",
            "streamingUrl": "https://web.afrahtafreeh.site/prepare/zGHLBbwdKbKsmDbW9fbM2Q?type=stream",
            "downloadUrl": "https://web.afrahtafreeh.site/prepare/zGHLBbwdKbKsmDbW9fbM2Q?type=download"
        },
        {
            "title": "29 HIV in pregnancy",
            "streamingUrl": "https://web.afrahtafreeh.site/prepare/f_Ez1KhCA3LJ5TyUFwPTUg?type=stream",
            "downloadUrl": "https://web.afrahtafreeh.site/prepare/f_Ez1KhCA3LJ5TyUFwPTUg?type=download"
        },
        {
            "title": "30 RH negative Pregnancy",
            "streamingUrl": "https://web.afrahtafreeh.site/prepare/mYC3XCALp3cvHBGgPlVEYA?type=stream",
            "downloadUrl": "https://web.afrahtafreeh.site/prepare/mYC3XCALp3cvHBGgPlVEYA?type=download"
        },
        {
            "title": "31 Twin Pregnancy part 1",
            "streamingUrl": "https://web.afrahtafreeh.site/prepare/9XFHFhiEWT72l0gCga6-Ww?type=stream",
            "downloadUrl": "https://web.afrahtafreeh.site/prepare/9XFHFhiEWT72l0gCga6-Ww?type=download"
        },
        {
            "title": "32 Twin Pregnancy Part 2",
            "streamingUrl": "https://web.afrahtafreeh.site/prepare/YslghddOaM4YKtqb8HR-vQ?type=stream",
            "downloadUrl": "https://web.afrahtafreeh.site/prepare/YslghddOaM4YKtqb8HR-vQ?type=download"
        },
        {
            "title": "33 Preterm Labor part 1",
            "streamingUrl": "https://web.afrahtafreeh.site/prepare/tU83AaIP0hi06CLAYkKNFg?type=stream",
            "downloadUrl": "https://web.afrahtafreeh.site/prepare/tU83AaIP0hi06CLAYkKNFg?type=download"
        },
        {
            "title": "34 Preterm labor part 2",
            "streamingUrl": "https://web.afrahtafreeh.site/prepare/zDb4S5N5CyaEWTVIdgdK1w?type=stream",
            "downloadUrl": "https://web.afrahtafreeh.site/prepare/zDb4S5N5CyaEWTVIdgdK1w?type=download"
        },
        {
            "title": "35. PROM",
            "streamingUrl": "https://web.afrahtafreeh.site/prepare/hZoIcQiWuxzJP4YATDEUwg?type=stream",
            "downloadUrl": "https://web.afrahtafreeh.site/prepare/hZoIcQiWuxzJP4YATDEUwg?type=download"
        },
        {
            "title": "36 Abortion: Part 1",
            "streamingUrl": "https://web.afrahtafreeh.site/prepare/KFAoKfI7K2aBJDVbKsLo3Q?type=stream",
            "downloadUrl": "https://web.afrahtafreeh.site/prepare/KFAoKfI7K2aBJDVbKsLo3Q?type=download"
        },
        {
            "title": "37 Abortion: Part 2",
            "streamingUrl": "https://web.afrahtafreeh.site/prepare/XXURNRR9pcddKKCo89VQww?type=stream",
            "downloadUrl": "https://web.afrahtafreeh.site/prepare/XXURNRR9pcddKKCo89VQww?type=download"
        },
        {
            "title": "38 Ectopic pregnancy. Part 1",
            "streamingUrl": "https://web.afrahtafreeh.site/prepare/JOiW8LL452yBg380jiQ2QQ?type=stream",
            "downloadUrl": "https://web.afrahtafreeh.site/prepare/JOiW8LL452yBg380jiQ2QQ?type=download"
        },
        {
            "title": "39 Ectopic pregnancy. Part 2",
            "streamingUrl": "https://web.afrahtafreeh.site/prepare/gf-QwTE60jBxAu9D-P_0Wg?type=stream",
            "downloadUrl": "https://web.afrahtafreeh.site/prepare/gf-QwTE60jBxAu9D-P_0Wg?type=download"
        },
        {
            "title": "40 Gestational trophoblastic disease",
            "streamingUrl": "https://web.afrahtafreeh.site/prepare/qFrlwaLHEtu0oXvhMI9d6A?type=stream",
            "downloadUrl": "https://web.afrahtafreeh.site/prepare/qFrlwaLHEtu0oXvhMI9d6A?type=download"
        },
        {
            "title": "41 Antepartum haemorrhage",
            "streamingUrl": "https://web.afrahtafreeh.site/prepare/aasQTGznrYrUco1dtmKRgQ?type=stream",
            "downloadUrl": "https://web.afrahtafreeh.site/prepare/aasQTGznrYrUco1dtmKRgQ?type=download"
        },
        {
            "title": "42 Placenta accreta spectrum",
            "streamingUrl": "https://web.afrahtafreeh.site/prepare/_kMwT7-I8Hv1P36mqXPKZw?type=stream",
            "downloadUrl": "https://web.afrahtafreeh.site/prepare/_kMwT7-I8Hv1P36mqXPKZw?type=download"
        },
        {
            "title": "43 Maternal pelvis",
            "streamingUrl": "https://web.afrahtafreeh.site/prepare/spoRDXlKd2WsrOj-Qrrnyg?type=stream",
            "downloadUrl": "https://web.afrahtafreeh.site/prepare/spoRDXlKd2WsrOj-Qrrnyg?type=download"
        },
        {
            "title": "44 Fetal skull",
            "streamingUrl": "https://web.afrahtafreeh.site/prepare/FMIoh6RzkK50YQNDeKlwqA?type=stream",
            "downloadUrl": "https://web.afrahtafreeh.site/prepare/FMIoh6RzkK50YQNDeKlwqA?type=download"
        },
        {
            "title": "45 Terminology related to labor",
            "streamingUrl": "https://web.afrahtafreeh.site/prepare/bR0u51WwilyV01f9DO-Hfw?type=stream",
            "downloadUrl": "https://web.afrahtafreeh.site/prepare/bR0u51WwilyV01f9DO-Hfw?type=download"
        },
        {
            "title": "46. Leopold Maneuver and antenatal examination",
            "streamingUrl": "https://web.afrahtafreeh.site/prepare/1A9UG-IWot_TXrVfWlPMYA?type=stream",
            "downloadUrl": "https://web.afrahtafreeh.site/prepare/1A9UG-IWot_TXrVfWlPMYA?type=download"
        },
        {
            "title": "47. Mechanism of labor",
            "streamingUrl": "https://web.afrahtafreeh.site/prepare/9lQA6s9dM64YKMHZahyPVw?type=stream",
            "downloadUrl": "https://web.afrahtafreeh.site/prepare/9lQA6s9dM64YKMHZahyPVw?type=download"
        },
        {
            "title": "48 Normal labor",
            "streamingUrl": "https://web.afrahtafreeh.site/prepare/Rt39A9dKtOVt-TM2AOmvYA?type=stream",
            "downloadUrl": "https://web.afrahtafreeh.site/prepare/Rt39A9dKtOVt-TM2AOmvYA?type=download"
        },
        {
            "title": "49. Induction of labor",
            "streamingUrl": "https://web.afrahtafreeh.site/prepare/fkFCjgx5F4l3dWypzrX2fw?type=stream",
            "downloadUrl": "https://web.afrahtafreeh.site/prepare/fkFCjgx5F4l3dWypzrX2fw?type=download"
        },
        {
            "title": "50. Stages of labor, Abnormal labor, Partogram part 1",
            "streamingUrl": "https://web.afrahtafreeh.site/prepare/UIzw7mePpV-bB87IDStJhg?type=stream",
            "downloadUrl": "https://web.afrahtafreeh.site/prepare/UIzw7mePpV-bB87IDStJhg?type=download"
        },
        {
            "title": "51 Stages of labor, Abnormal labor and Partogram: Part 2",
            "streamingUrl": "https://web.afrahtafreeh.site/prepare/phFzhMkyjMrDGOmMCNoaQg?type=stream",
            "downloadUrl": "https://web.afrahtafreeh.site/prepare/phFzhMkyjMrDGOmMCNoaQg?type=download"
        },
        {
            "title": "52 Complications of third stage of labor - PPH",
            "streamingUrl": "https://web.afrahtafreeh.site/prepare/0cfAptz99p0YDDtg4pA5zg?type=stream",
            "downloadUrl": "https://web.afrahtafreeh.site/prepare/0cfAptz99p0YDDtg4pA5zg?type=download"
        },
        {
            "title": "53. Other complications of third stage of labor",
            "streamingUrl": "https://web.afrahtafreeh.site/prepare/LW27CiXcXTgmeZ9EMBgXJA?type=stream",
            "downloadUrl": "https://web.afrahtafreeh.site/prepare/LW27CiXcXTgmeZ9EMBgXJA?type=download"
        },
        {
            "title": "54. Malpresentation part 1",
            "streamingUrl": "https://web.afrahtafreeh.site/prepare/vxgnTiBnT2GkOwjFTE-shA?type=stream",
            "downloadUrl": "https://web.afrahtafreeh.site/prepare/vxgnTiBnT2GkOwjFTE-shA?type=download"
        },
        {
            "title": "55. Malpresentation part 2",
            "streamingUrl": "https://web.afrahtafreeh.site/prepare/tldlhtZV_zAPEPsuMl_E7w?type=stream",
            "downloadUrl": "https://web.afrahtafreeh.site/prepare/tldlhtZV_zAPEPsuMl_E7w?type=download"
        },
        {
            "title": "56. Instrumental delivery",
            "streamingUrl": "https://web.afrahtafreeh.site/prepare/UpyK6PX3ichu_yj_ZncQVQ?type=stream",
            "downloadUrl": "https://web.afrahtafreeh.site/prepare/UpyK6PX3ichu_yj_ZncQVQ?type=download"
        },
        {
            "title": "57 Cesarean section",
            "streamingUrl": "https://web.afrahtafreeh.site/prepare/To9dJCmTHGUGQPKrD--zkg?type=stream",
            "downloadUrl": "https://web.afrahtafreeh.site/prepare/To9dJCmTHGUGQPKrD--zkg?type=download"
        },
        {
            "title": "59. Menstrual Cycle",
            "streamingUrl": "https://web.afrahtafreeh.site/prepare/x6-HyG4P7ISVkW49VT2eIQ?type=stream",
            "downloadUrl": "https://web.afrahtafreeh.site/prepare/x6-HyG4P7ISVkW49VT2eIQ?type=download"
        },
        {
            "title": "60. Atypical Uterine bleeding part 1",
            "streamingUrl": "https://web.afrahtafreeh.site/prepare/XeoI0l9upTK0BBJOB6Fxxg?type=stream",
            "downloadUrl": "https://web.afrahtafreeh.site/prepare/XeoI0l9upTK0BBJOB6Fxxg?type=download"
        },
        {
            "title": "61. Atypical Uterine bleeding Part 2",
            "streamingUrl": "https://web.afrahtafreeh.site/prepare/5U_wIA6n1B406blKC8x3ow?type=stream",
            "downloadUrl": "https://web.afrahtafreeh.site/prepare/5U_wIA6n1B406blKC8x3ow?type=download"
        },
        {
            "title": "62. Dysmenorrhea",
            "streamingUrl": "https://web.afrahtafreeh.site/prepare/AknwJJxQUbBy0IQGKDIyXQ?type=stream",
            "downloadUrl": "https://web.afrahtafreeh.site/prepare/AknwJJxQUbBy0IQGKDIyXQ?type=download"
        },
        {
            "title": "63. Gynecology Anatomy Integration part 1",
            "streamingUrl": "https://web.afrahtafreeh.site/prepare/q3sQaALZiTm1d7Bm0QnEfw?type=stream",
            "downloadUrl": "https://web.afrahtafreeh.site/prepare/q3sQaALZiTm1d7Bm0QnEfw?type=download"
        },
        {
            "title": "64. Gynecology Anatomy Integration Part 2",
            "streamingUrl": "https://web.afrahtafreeh.site/prepare/7iqfMDfqJkA9_8GcOz7B7Q?type=stream",
            "downloadUrl": "https://web.afrahtafreeh.site/prepare/7iqfMDfqJkA9_8GcOz7B7Q?type=download"
        },
        {
            "title": "65. Gynecology Anatomy Integration Part 3",
            "streamingUrl": "https://web.afrahtafreeh.site/prepare/YqF3Fs1xei_5gbShhdsFLA?type=stream",
            "downloadUrl": "https://web.afrahtafreeh.site/prepare/YqF3Fs1xei_5gbShhdsFLA?type=download"
        },
        {
            "title": "66. Gynecology Anatomy Integration Part 4",
            "streamingUrl": "https://web.afrahtafreeh.site/prepare/n37I8cHtdr_bypVFBaRPAg?type=stream",
            "downloadUrl": "https://web.afrahtafreeh.site/prepare/n37I8cHtdr_bypVFBaRPAg?type=download"
        },
        {
            "title": "67. Gynecology Physiology Integration Part 1",
            "streamingUrl": "https://web.afrahtafreeh.site/prepare/uJB9_c0KDkxc6RycpmzqfA?type=stream",
            "downloadUrl": "https://web.afrahtafreeh.site/prepare/uJB9_c0KDkxc6RycpmzqfA?type=download"
        },
        {
            "title": "68. Gynecology Physiology Integration Part 2",
            "streamingUrl": "https://web.afrahtafreeh.site/prepare/dtQqhHZdnprMFmPv_qvR7A?type=stream",
            "downloadUrl": "https://web.afrahtafreeh.site/prepare/dtQqhHZdnprMFmPv_qvR7A?type=download"
        },
        {
            "title": "69. Gynecology Pharmacology Integration part 1",
            "streamingUrl": "https://web.afrahtafreeh.site/prepare/GqK5tC4vrtSNp2U_LwUHGw?type=stream",
            "downloadUrl": "https://web.afrahtafreeh.site/prepare/GqK5tC4vrtSNp2U_LwUHGw?type=download"
        },
        {
            "title": "70. Gynecology Pharmacology Integration part 2",
            "streamingUrl": "https://web.afrahtafreeh.site/prepare/SzyXN9U6aG3QCmuBEPRG0g?type=stream",
            "downloadUrl": "https://web.afrahtafreeh.site/prepare/SzyXN9U6aG3QCmuBEPRG0g?type=download"
        },
        {
            "title": "71. Gynecology Pharmacology Integration part 3",
            "streamingUrl": "https://web.afrahtafreeh.site/prepare/DYn3VOYb23z9m7XisdsYPg?type=stream",
            "downloadUrl": "https://web.afrahtafreeh.site/prepare/DYn3VOYb23z9m7XisdsYPg?type=download"
        },
        {
            "title": "72. Gynecology Pathology integration part 1",
            "streamingUrl": "https://web.afrahtafreeh.site/prepare/vFfz_bCv3FV_n61KpqV3UA?type=stream",
            "downloadUrl": "https://web.afrahtafreeh.site/prepare/vFfz_bCv3FV_n61KpqV3UA?type=download"
        },
        {
            "title": "73. Gynecology Pathology Integration part 2",
            "streamingUrl": "https://web.afrahtafreeh.site/prepare/kT8FMPly6dBn8P6aBVUTuQ?type=stream",
            "downloadUrl": "https://web.afrahtafreeh.site/prepare/kT8FMPly6dBn8P6aBVUTuQ?type=download"
        },
        {
            "title": "74. Menopause",
            "streamingUrl": "https://web.afrahtafreeh.site/prepare/0I1hIWBT-M_AjaMzu5k1qQ?type=stream",
            "downloadUrl": "https://web.afrahtafreeh.site/prepare/0I1hIWBT-M_AjaMzu5k1qQ?type=download"
        },
        {
            "title": "75. Pcos part 1",
            "streamingUrl": "https://web.afrahtafreeh.site/prepare/CcP5hcuUI6dZdsLSXT_ufA?type=stream",
            "downloadUrl": "https://web.afrahtafreeh.site/prepare/CcP5hcuUI6dZdsLSXT_ufA?type=download"
        },
        {
            "title": "76. PCOS PART 2",
            "streamingUrl": "https://web.afrahtafreeh.site/prepare/1wD7AZldSBHA4Sreh_ItDw?type=stream",
            "downloadUrl": "https://web.afrahtafreeh.site/prepare/1wD7AZldSBHA4Sreh_ItDw?type=download"
        },
        {
            "title": "77. Endometrosis",
            "streamingUrl": "https://web.afrahtafreeh.site/prepare/C2QXcWyTR2IHxtk02XEshg?type=stream",
            "downloadUrl": "https://web.afrahtafreeh.site/prepare/C2QXcWyTR2IHxtk02XEshg?type=download"
        },
        {
            "title": "78. Fibroid Part 1",
            "streamingUrl": "https://web.afrahtafreeh.site/prepare/hBA_9Zs5BH1RXy0s-JounA?type=stream",
            "downloadUrl": "https://web.afrahtafreeh.site/prepare/hBA_9Zs5BH1RXy0s-JounA?type=download"
        },
        {
            "title": "79. Fibroid part 2",
            "streamingUrl": "https://web.afrahtafreeh.site/prepare/Ij7vfOyglxPMv6z_dNJflw?type=stream",
            "downloadUrl": "https://web.afrahtafreeh.site/prepare/Ij7vfOyglxPMv6z_dNJflw?type=download"
        },
        {
            "title": "80. Polyp and adenomyosis",
            "streamingUrl": "https://web.afrahtafreeh.site/prepare/GHal5TfxEhJk89L88yAoGw?type=stream",
            "downloadUrl": "https://web.afrahtafreeh.site/prepare/GHal5TfxEhJk89L88yAoGw?type=download"
        },
        {
            "title": "81. Congenital Malformations of uterus",
            "streamingUrl": "https://web.afrahtafreeh.site/prepare/4qaKE4tuVk6mZv8L-K5b8g?type=stream",
            "downloadUrl": "https://web.afrahtafreeh.site/prepare/4qaKE4tuVk6mZv8L-K5b8g?type=download"
        },
        {
            "title": "82. Prolapse",
            "streamingUrl": "https://web.afrahtafreeh.site/prepare/mqrwS-ueThfnjHYpPA-sdg?type=stream",
            "downloadUrl": "https://web.afrahtafreeh.site/prepare/mqrwS-ueThfnjHYpPA-sdg?type=download"
        },
        {
            "title": "83. Stress urinary incontinence",
            "streamingUrl": "https://web.afrahtafreeh.site/prepare/UKIZRJM48zXpfAWQoK9zrg?type=stream",
            "downloadUrl": "https://web.afrahtafreeh.site/prepare/UKIZRJM48zXpfAWQoK9zrg?type=download"
        },
        {
            "title": "84. Urinary Fistulas",
            "streamingUrl": "https://web.afrahtafreeh.site/prepare/qrcBbfoN5rm995x7Viy8_w?type=stream",
            "downloadUrl": "https://web.afrahtafreeh.site/prepare/qrcBbfoN5rm995x7Viy8_w?type=download"
        },
        {
            "title": "85. Normal sexual development",
            "streamingUrl": "https://web.afrahtafreeh.site/prepare/au7ZF0y6bd3TIW0mJ1zsWg?type=stream",
            "downloadUrl": "https://web.afrahtafreeh.site/prepare/au7ZF0y6bd3TIW0mJ1zsWg?type=download"
        },
        {
            "title": "86. Puberty",
            "streamingUrl": "https://web.afrahtafreeh.site/prepare/tKezuTTRvpJmoVt6MZfGug?type=stream",
            "downloadUrl": "https://web.afrahtafreeh.site/prepare/tKezuTTRvpJmoVt6MZfGug?type=download"
        },
        {
            "title": "87. Disorders of sexual development part 1",
            "streamingUrl": "https://web.afrahtafreeh.site/prepare/ZFplEXCBlB_Ao7iijMDBlg?type=stream",
            "downloadUrl": "https://web.afrahtafreeh.site/prepare/ZFplEXCBlB_Ao7iijMDBlg?type=download"
        },
        {
            "title": "88. Disorders of sexual development part 2",
            "streamingUrl": "https://web.afrahtafreeh.site/prepare/dEY48JRS6ljkjfd3goB4ig?type=stream",
            "downloadUrl": "https://web.afrahtafreeh.site/prepare/dEY48JRS6ljkjfd3goB4ig?type=download"
        },
        {
            "title": "89. Primary Amenorrhea",
            "streamingUrl": "https://web.afrahtafreeh.site/prepare/RVZ-1eExNrRgSyCLF-fo-w?type=stream",
            "downloadUrl": "https://web.afrahtafreeh.site/prepare/RVZ-1eExNrRgSyCLF-fo-w?type=download"
        },
        {
            "title": "90. secondary amenorrhea",
            "streamingUrl": "https://web.afrahtafreeh.site/prepare/YWJ0IkOVW0U19F2dldUnFA?type=stream",
            "downloadUrl": "https://web.afrahtafreeh.site/prepare/YWJ0IkOVW0U19F2dldUnFA?type=download"
        },
        {
            "title": "91. Vaginitis",
            "streamingUrl": "https://web.afrahtafreeh.site/prepare/AUnCaWFewEF8FqT2EU4QyA?type=stream",
            "downloadUrl": "https://web.afrahtafreeh.site/prepare/AUnCaWFewEF8FqT2EU4QyA?type=download"
        },
        {
            "title": "92. PID",
            "streamingUrl": "https://web.afrahtafreeh.site/prepare/QW3T6EfBuXJudWpCtmc83A?type=stream",
            "downloadUrl": "https://web.afrahtafreeh.site/prepare/QW3T6EfBuXJudWpCtmc83A?type=download"
        },
        {
            "title": "93. Genital TB",
            "streamingUrl": "https://web.afrahtafreeh.site/prepare/QPjSb39RJcjxZJe0aYnyow?type=stream",
            "downloadUrl": "https://web.afrahtafreeh.site/prepare/QPjSb39RJcjxZJe0aYnyow?type=download"
        },
        {
            "title": "94. Female Infertility",
            "streamingUrl": "https://web.afrahtafreeh.site/prepare/JPN4oUHaIKtXUHA7SLTPgA?type=stream",
            "downloadUrl": "https://web.afrahtafreeh.site/prepare/JPN4oUHaIKtXUHA7SLTPgA?type=download"
        },
        {
            "title": "95. Male infertility",
            "streamingUrl": "https://web.afrahtafreeh.site/prepare/ZHucUTeGdx_UEChbx8zWvA?type=stream",
            "downloadUrl": "https://web.afrahtafreeh.site/prepare/ZHucUTeGdx_UEChbx8zWvA?type=download"
        },
        {
            "title": "96. Natural Methods of Contraception",
            "streamingUrl": "https://web.afrahtafreeh.site/prepare/CMwtWNoDglIJJARhDgNmfg?type=stream",
            "downloadUrl": "https://web.afrahtafreeh.site/prepare/CMwtWNoDglIJJARhDgNmfg?type=download"
        },
        {
            "title": "97. Barrier Methods of contraception",
            "streamingUrl": "https://web.afrahtafreeh.site/prepare/moVSw-c4OgQefrODbvR8sQ?type=stream",
            "downloadUrl": "https://web.afrahtafreeh.site/prepare/moVSw-c4OgQefrODbvR8sQ?type=download"
        },
        {
            "title": "98 Estrogen and Progesterone contraceptives",
            "streamingUrl": "https://web.afrahtafreeh.site/prepare/EzoaFSU5B23wD-jHxq0UAg?type=stream",
            "downloadUrl": "https://web.afrahtafreeh.site/prepare/EzoaFSU5B23wD-jHxq0UAg?type=download"
        },
        {
            "title": "99 Only Progesterone contraceptives",
            "streamingUrl": "https://web.afrahtafreeh.site/prepare/6lTegocORqxoM5H4itBDUA?type=stream",
            "downloadUrl": "https://web.afrahtafreeh.site/prepare/6lTegocORqxoM5H4itBDUA?type=download"
        },
        {
            "title": "100 IUCDS",
            "streamingUrl": "https://web.afrahtafreeh.site/prepare/6UWMRtE_CRHfWAzclEMigA?type=stream",
            "downloadUrl": "https://web.afrahtafreeh.site/prepare/6UWMRtE_CRHfWAzclEMigA?type=download"
        },
        {
            "title": "101 Permanent methods of contraception",
            "streamingUrl": "https://web.afrahtafreeh.site/prepare/SgE4yv7yVmrGATiD1BNARQ?type=stream",
            "downloadUrl": "https://web.afrahtafreeh.site/prepare/SgE4yv7yVmrGATiD1BNARQ?type=download"
        },
        {
            "title": "102 Miscellaneous contraception",
            "streamingUrl": "https://web.afrahtafreeh.site/prepare/qzOAYSfJVqOT8H-xRK7_7A?type=stream",
            "downloadUrl": "https://web.afrahtafreeh.site/prepare/qzOAYSfJVqOT8H-xRK7_7A?type=download"
        },
        {
            "title": "103. Endometrial Hyperplasia",
            "streamingUrl": "https://web.afrahtafreeh.site/prepare/YzNbTXdYNonU5L-higxCSw?type=stream",
            "downloadUrl": "https://web.afrahtafreeh.site/prepare/YzNbTXdYNonU5L-higxCSw?type=download"
        },
        {
            "title": "104. Endometrial Cancer",
            "streamingUrl": "https://web.afrahtafreeh.site/prepare/H3FTqxPW37d1u6Oo8RBFcA?type=stream",
            "downloadUrl": "https://web.afrahtafreeh.site/prepare/H3FTqxPW37d1u6Oo8RBFcA?type=download"
        },
        {
            "title": "105. CIN Part 1",
            "streamingUrl": "https://web.afrahtafreeh.site/prepare/iptOgZZRRQ0SjJZLdKnIPg?type=stream",
            "downloadUrl": "https://web.afrahtafreeh.site/prepare/iptOgZZRRQ0SjJZLdKnIPg?type=download"
        },
        {
            "title": "106. CIN PART 2",
            "streamingUrl": "https://web.afrahtafreeh.site/prepare/irt8MsphYZ5TajPUqSHGag?type=stream",
            "downloadUrl": "https://web.afrahtafreeh.site/prepare/irt8MsphYZ5TajPUqSHGag?type=download"
        },
        {
            "title": "107. Cancer cervix",
            "streamingUrl": "https://web.afrahtafreeh.site/prepare/Q9_9pB__SzCWZC4qADyhDA?type=stream",
            "downloadUrl": "https://web.afrahtafreeh.site/prepare/Q9_9pB__SzCWZC4qADyhDA?type=download"
        },
        {
            "title": "108 Ovarian cancer. Part 1",
            "streamingUrl": "https://web.afrahtafreeh.site/prepare/vn6iwFfsuic-z1_0h4P2gA?type=stream",
            "downloadUrl": "https://web.afrahtafreeh.site/prepare/vn6iwFfsuic-z1_0h4P2gA?type=download"
        },
        {
            "title": "109 Ovarian cancer. Part 2",
            "streamingUrl": "https://web.afrahtafreeh.site/prepare/gFBLpvJrRKOZUZ6m97ft9Q?type=stream",
            "downloadUrl": "https://web.afrahtafreeh.site/prepare/gFBLpvJrRKOZUZ6m97ft9Q?type=download"
        },
        {
            "title": "110 Vulval cancer",
            "streamingUrl": "https://web.afrahtafreeh.site/prepare/zOZhoQLC7RbMLBuReOxyvg?type=stream",
            "downloadUrl": "https://web.afrahtafreeh.site/prepare/zOZhoQLC7RbMLBuReOxyvg?type=download"
        }
    ],
    "skipped": []
}