{
    "subjectName": "dhfmt",
    "lectures": [
        {
            "title": "1 Introduction to Forensic Medicine and Ethics atf.mp4",
            "streamingUrl": "https://web.afrahtafreeh.site/prepare/IKsoQf31DO6Eejug2QtxqA?type=stream",
            "downloadUrl": "https://web.afrahtafreeh.site/prepare/IKsoQf31DO6Eejug2QtxqA?type=download"
        },
        {
            "title": "1.1 Introduction to Forensic Medicine and Ethics Questions atf.mp4",
            "streamingUrl": "https://web.afrahtafreeh.site/prepare/Bfh3MxycpJ2ONTYt6K3pWw?type=stream",
            "downloadUrl": "https://web.afrahtafreeh.site/prepare/Bfh3MxycpJ2ONTYt6K3pWw?type=download"
        },
        {
            "title": "2 Legal Procedures atf.mp4",
            "streamingUrl": "https://web.afrahtafreeh.site/prepare/H30sCFHSFZEJGjQg6uy5Cw?type=stream",
            "downloadUrl": "https://web.afrahtafreeh.site/prepare/H30sCFHSFZEJGjQg6uy5Cw?type=download"
        },
        {
            "title": "2.1 Legal Procedures Questions atf.mp4",
            "streamingUrl": "https://web.afrahtafreeh.site/prepare/Xv05Z0mV1GDMKu1cR5l2Dg?type=stream",
            "downloadUrl": "https://web.afrahtafreeh.site/prepare/Xv05Z0mV1GDMKu1cR5l2Dg?type=download"
        },
        {
            "title": "3.Consent atf.mp4",
            "streamingUrl": "https://web.afrahtafreeh.site/prepare/0zWyvQiNQOaLB8drqpTmcQ?type=stream",
            "downloadUrl": "https://web.afrahtafreeh.site/prepare/0zWyvQiNQOaLB8drqpTmcQ?type=download"
        },
        {
            "title": "3.1 Consent Questions atf.mp4",
            "streamingUrl": "https://web.afrahtafreeh.site/prepare/roxhWipfiodC4rOLAl5Xmw?type=stream",
            "downloadUrl": "https://web.afrahtafreeh.site/prepare/roxhWipfiodC4rOLAl5Xmw?type=download"
        },
        {
            "title": "4.Negligence atf.mp4",
            "streamingUrl": "https://web.afrahtafreeh.site/prepare/_6RbRBuzh1I2-2mSqzvE8A?type=stream",
            "downloadUrl": "https://web.afrahtafreeh.site/prepare/_6RbRBuzh1I2-2mSqzvE8A?type=download"
        },
        {
            "title": "4. 1 Negligence MCQ atf.mp4",
            "streamingUrl": "https://web.afrahtafreeh.site/prepare/RusWLehCgD1xCx231UaU3Q?type=stream",
            "downloadUrl": "https://web.afrahtafreeh.site/prepare/RusWLehCgD1xCx231UaU3Q?type=download"
        },
        {
            "title": "5. IPC Sections atf.mp4",
            "streamingUrl": "https://web.afrahtafreeh.site/prepare/P7ujz9Al-ZtYt8AkNhYX-A?type=stream",
            "downloadUrl": "https://web.afrahtafreeh.site/prepare/P7ujz9Al-ZtYt8AkNhYX-A?type=download"
        },
        {
            "title": "5.1 IPC QUESTIONS atf.mp4",
            "streamingUrl": "https://web.afrahtafreeh.site/prepare/7lZwE9wcNurWngpXASZSOQ?type=stream",
            "downloadUrl": "https://web.afrahtafreeh.site/prepare/7lZwE9wcNurWngpXASZSOQ?type=download"
        },
        {
            "title": "6.Identification atf.mp4",
            "streamingUrl": "https://web.afrahtafreeh.site/prepare/ytHPrvX7L8FvuKtGnUlc-A?type=stream",
            "downloadUrl": "https://web.afrahtafreeh.site/prepare/ytHPrvX7L8FvuKtGnUlc-A?type=download"
        },
        {
            "title": "6.1 Identification MCQ atf.mp4",
            "streamingUrl": "https://web.afrahtafreeh.site/prepare/5NgFgzzb6hKoSVqi10MNeQ?type=stream",
            "downloadUrl": "https://web.afrahtafreeh.site/prepare/5NgFgzzb6hKoSVqi10MNeQ?type=download"
        },
        {
            "title": "7.Thanatology atf.mp4",
            "streamingUrl": "https://web.afrahtafreeh.site/prepare/zj-_EvArTNfgw7YYcT-m2Q?type=stream",
            "downloadUrl": "https://web.afrahtafreeh.site/prepare/zj-_EvArTNfgw7YYcT-m2Q?type=download"
        },
        {
            "title": "7.1 Thanatology Question atf.mp4",
            "streamingUrl": "https://web.afrahtafreeh.site/prepare/2O_l_tQZ02WLYG0-T5eHrw?type=stream",
            "downloadUrl": "https://web.afrahtafreeh.site/prepare/2O_l_tQZ02WLYG0-T5eHrw?type=download"
        },
        {
            "title": "8. Acts atf.mp4",
            "streamingUrl": "https://web.afrahtafreeh.site/prepare/SipLpNXOhuhEEWppcQD8qg?type=stream",
            "downloadUrl": "https://web.afrahtafreeh.site/prepare/SipLpNXOhuhEEWppcQD8qg?type=download"
        },
        {
            "title": "9.Mechanical Injuries atf.mp4",
            "streamingUrl": "https://web.afrahtafreeh.site/prepare/E0Hgai0Teocp_gM1FrAUkA?type=stream",
            "downloadUrl": "https://web.afrahtafreeh.site/prepare/E0Hgai0Teocp_gM1FrAUkA?type=download"
        },
        {
            "title": "9.1 Mechanical Injuries MCQ atf.mp4",
            "streamingUrl": "https://web.afrahtafreeh.site/prepare/N7rsWBh_MZIW0AujYcxk8Q?type=stream",
            "downloadUrl": "https://web.afrahtafreeh.site/prepare/N7rsWBh_MZIW0AujYcxk8Q?type=download"
        },
        {
            "title": "10. Forensic Ballistics atf.mp4",
            "streamingUrl": "https://web.afrahtafreeh.site/prepare/HzrJbhUYewdn-SNniu_2Gw?type=stream",
            "downloadUrl": "https://web.afrahtafreeh.site/prepare/HzrJbhUYewdn-SNniu_2Gw?type=download"
        },
        {
            "title": "10.1 Forensic Ballistics MCQ atf.mp4",
            "streamingUrl": "https://web.afrahtafreeh.site/prepare/ri9VCMK-fg5-d3Eh8iBB5A?type=stream",
            "downloadUrl": "https://web.afrahtafreeh.site/prepare/ri9VCMK-fg5-d3Eh8iBB5A?type=download"
        },
        {
            "title": "11.Asphyxia atf.mp4",
            "streamingUrl": "https://web.afrahtafreeh.site/prepare/sOrcKkkuzJyqAhdUygMf3g?type=stream",
            "downloadUrl": "https://web.afrahtafreeh.site/prepare/sOrcKkkuzJyqAhdUygMf3g?type=download"
        },
        {
            "title": "11.1 Asphyxial questions.mp4",
            "streamingUrl": "https://web.afrahtafreeh.site/prepare/P9ar8nXEFWIP-3Kx-BBRjw?type=stream",
            "downloadUrl": "https://web.afrahtafreeh.site/prepare/P9ar8nXEFWIP-3Kx-BBRjw?type=download"
        },
        {
            "title": "12. Thrmeal Injuries atf.mp4",
            "streamingUrl": "https://web.afrahtafreeh.site/prepare/j7z8-vTvZEBViArtXBc9vw?type=stream",
            "downloadUrl": "https://web.afrahtafreeh.site/prepare/j7z8-vTvZEBViArtXBc9vw?type=download"
        },
        {
            "title": "12.1 Thermial Injuries Questions atf.mp4",
            "streamingUrl": "https://web.afrahtafreeh.site/prepare/f3H_9b8sk-bN5gwtY7AulQ?type=stream",
            "downloadUrl": "https://web.afrahtafreeh.site/prepare/f3H_9b8sk-bN5gwtY7AulQ?type=download"
        },
        {
            "title": "13. Impotance and Sterilite atf.mp4",
            "streamingUrl": "https://web.afrahtafreeh.site/prepare/Ex3bbDLFX0i18FTC5PrZCg?type=stream",
            "downloadUrl": "https://web.afrahtafreeh.site/prepare/Ex3bbDLFX0i18FTC5PrZCg?type=download"
        },
        {
            "title": "13.1 Impotance and Sterilite Questions atf.mp4",
            "streamingUrl": "https://web.afrahtafreeh.site/prepare/0eS6sGgQRDzyiBY6oZL-XQ?type=stream",
            "downloadUrl": "https://web.afrahtafreeh.site/prepare/0eS6sGgQRDzyiBY6oZL-XQ?type=download"
        },
        {
            "title": "14.Autopsy Infanticide Stain atf.mp4",
            "streamingUrl": "https://web.afrahtafreeh.site/prepare/I-DRcLb50vvWR3ZJye-72A?type=stream",
            "downloadUrl": "https://web.afrahtafreeh.site/prepare/I-DRcLb50vvWR3ZJye-72A?type=download"
        },
        {
            "title": "14.1 Autopsy Infanticide Stain Question atf.mp4",
            "streamingUrl": "https://web.afrahtafreeh.site/prepare/ERlmcledOLYPmN5GUpaUkw?type=stream",
            "downloadUrl": "https://web.afrahtafreeh.site/prepare/ERlmcledOLYPmN5GUpaUkw?type=download"
        },
        {
            "title": "15.Toxicology atf.mp4",
            "streamingUrl": "https://web.afrahtafreeh.site/prepare/jVPqaYC58rXQ0x4b-eghyQ?type=stream",
            "downloadUrl": "https://web.afrahtafreeh.site/prepare/jVPqaYC58rXQ0x4b-eghyQ?type=download"
        },
        {
            "title": "15.1 Toxicology Questions atf.mp4",
            "streamingUrl": "https://web.afrahtafreeh.site/prepare/g26LMkFBB5Ebtt2EnbbfUA?type=stream",
            "downloadUrl": "https://web.afrahtafreeh.site/prepare/g26LMkFBB5Ebtt2EnbbfUA?type=download"
        }
    ],
    "skipped": []
}